{
    "AzureResourceManagerDnsSuffix": "adminmanagement.local.azurestack.external",
    "TenantAzureResourceManagerDnsSuffix": "management.local.azurestack.external",
    "AzureDirectoryTenantName": "aimless2.onmicrosoft.com",
    "IdentityApplicationId": "<<IdentityApplicationId>>",
    "VirtualNetwork": {
        "name": "aps-vnet",
        "properties": {
            "addressSpace": {
                "addressPrefixes": [
                    "10.0.0.0/16"
                ]
            }
        }
    },
    "ControllersSubnet": {
        "name": "ControllerSubnet",
        "properties": {
            "addressPrefix": "10.0.3.0/24"
        }
    },
    "ManagementServersSubnet": {
        "name": "ManagementSubnet",
        "properties": {
            "addressPrefix": "10.0.4.0/24"
        }
    },
    "FrontEndsSubnet": {
        "name": "FrontendSubnet",
        "properties": {
            "addressPrefix": "10.0.6.0/24"
        }
    },
    "PublishersSubnet": {
        "name": "PublisherSubnet",
        "properties": {
            "addressPrefix": "10.0.5.0/24"
        }
    },
    "WorkersSubnet": {
        "name": "WorkerSubnet",
        "properties": {
            "addressPrefix": "10.0.8.0/24"
        }
    },
    "SelectedControllerSKUs": {
        "name": "Standard_A2"
    },
    "SelectedManagementRoleSKUs": {
        "name": "Standard_A2"
    },
    "SelectedPublisherRoleSKUs": {
        "name": "Standard_A2"
    },
    "SelectedFrontEndRoleSKUs": {
        "name": "Standard_A2"
    },
    "SelectedWorkerSKUs": {
        "name": "Standard_A2"
    },
    "SelectedSmallWorkerSKUs": {
        "name": "Standard_A1_v2"
    },
    "SelectedMediumWorkerSKUs": {
        "name": "Standard_A2"
    },
    "SelectedLargeWorkerSKUs": {
        "name": "Standard_A3"
    },
    "FileShareUNCPath": "\\\\fs01.appsvc.local\\Websites",
    "FileServerSKUs": "Standard_A1",
    "FileShareOwner": "appsvc.local\\FileShareOwner",
    "FileShareOwnerPassword": "P@ssw0rd000000",
    "FileShareUser": "appsvc.local\\FileShareUser",
    "FileShareUserPassword": "P@ssw0rd000000",
    "ResourceGroupName": "apps-infra",
    "StorageAccountName": "appsvclocalstor",
    "IdentityPfxCertPath": "C:\\Users\\appsvcadmin.APS-SQL-0\\Documents\\sso.appservice.local.azurestack.external.pfx",
    "IdentityPfxCertPassword": "P@ssw0rdP@ssw0rd",
    "RootCertPath": "C:\\Users\\appsvcadmin.APS-SQL-0\\Documents\\AzureStackCertificationAuthority.cer",
    "DefaultPfxCertPath": "C:\\Users\\appsvcadmin.APS-SQL-0\\Documents\\_.appservice.local.azurestack.external.pfx",
    "DefaultPfxCertPassword": "P@ssw0rdP@ssw0rd",
    "ResourceProviderPfxCertPath": "C:\\Users\\appsvcadmin.APS-SQL-0\\Documents\\api.appservice.local.azurestack.external.pfx",
    "ResourceProviderPfxCertPassword": "P@ssw0rdP@ssw0rd",
    "PublisherPfxCertPath": "C:\\Users\\appsvcadmin.APS-SQL-0\\Documents\\ftp.appservice.local.azurestack.external.pfx",
    "PublisherPfxCertPassword": "P@ssw0rdP@ssw0rd",
    "SQLServerName": "10.0.1.100",
    "SQLSysAdminLogin": "sqlsa",
    "SQLSysAdminPassword": "P@ssw0rd000000",
    "SelectedControllerInstances": 1,
    "SelectedManagementRoleInstances": 1,
    "SelectedPublisherRoleInstances": 1,
    "SelectedFrontEndRoleInstances": 1,
    "SelectedWorkerInstances": 1,
    "PlatformImage": {
        "Publisher": "MicrosoftWindowsServer",
        "Offer": "WindowsServer",
        "name": "2016-Datacenter",
        "Version": "latest"
    },
    "WorkerVirtualMachineAdministrator": "workeradmin",
    "WorkerVirtualMachinePassword": "P@ssw0rdP@ssw0rd",
    "OtherVirtualMachineAdministrator": "roleadmin",
    "OtherVirtualMachinePassword": "P@ssw0rdP@ssw0rd"
}
